{
  "parent": "minecraft:recipes/root",
  "rewards": {
    "recipes": [
      "campanion:pink_lawn_chair"
    ]
  },
  "criteria": {
    "has_pink_carpet": {
      "trigger": "minecraft:inventory_changed",
      "conditions": {
        "items": [
          {
            "items": [ "minecraft:pink_carpet" ]
          }
        ]
      }
    },
    "has_the_recipe": {
      "trigger": "minecraft:recipe_unlocked",
      "conditions": {
        "recipe": "campanion:pink_lawn_chair"
      }
    }
  },
  "requirements": [
    [
      "has_pink_carpet",
      "has_the_recipe"
    ]
  ]
}
